zbsmsa/__init__.py
zbsmsa/page.py
zbsmsa/site.py
zbsmsa/inventory/__init__.py
zbsmsa/inventory/stock.py
zbsmsa/utils/__init__.py
zbsmsa/utils/constants.py
zbsmsa/utils/decorators.py
zbsmsa/utils/exceptions.py
zbsmsa/utils/utilities.py
zbsmsa/utils/waits.py
zbsmsa/utils/json/__init__.py
zbsmsa/utils/json/adjustStock.json
zbsmsa/utils/json/loginPage.json
zbsmsa/utils/json/mainPage.json
zbsmsa/utils/json/prodChooser.json
zbsmsa/utils/json/siteSettings.json
zbsmsa/utils/json/stockTab.json
zbsmsa/utils/json/stockTabMutate.json
zbsmsa/utils/json/stockTabTable.json
zbsmsa/utils/json/userSettings.json
zbsmsa-1.0.10.dist-info/DESCRIPTION.rst
zbsmsa-1.0.10.dist-info/METADATA
zbsmsa-1.0.10.dist-info/RECORD
zbsmsa-1.0.10.dist-info/WHEEL
zbsmsa-1.0.10.dist-info/metadata.json
zbsmsa-1.0.10.dist-info/top_level.txt
zbsmsa-1.0.10.dist-info/zip-safe
